Workbook

Sheet Inicio
A1: TerraExport · Modelo de cálculo
A2: EIF409 Aplicaciones Informáticas Globales, UNA Campus Liberia, II Ciclo 2026
A4: Qué es | B4: Muestra de datos (10 países, 15 productos) y reglas de cálculo aplicadas a 10 casos. La demo usa estos mismos datos.
A5: Cómo leer | B5: Texto azul: dato editable. Texto negro: fórmula. La columna Estado indica de dónde sale cada dato.
A6: Estados | B6: Verificado: fuente oficial o secundaria del 2026. Referencia / Derivado: dato de años anteriores o calculado a partir de una fuente. Estimado: valor de mercado sin fuente pública directa.
A7: Fórmulas | B7: FOB = volumen × costo unitario · Flete = volumen × kg × USD/kg · Seguro = (FOB + flete) × % · CIF = FOB + flete + seguro · Arancel = CIF × % · Costo total = CIF + arancel · Unidades vendidas = MÍN(volumen; ENTERO(demanda ÷ equipos × índice^−elasticidad)) · Utilidad = ventas − costo total. Todo se redondea a 2 decimales.
A8: Actualizar la demo | B8: Guardar en Excel → python scripts/excel_a_datos.py → npm test.
A11: Hojas
A12: Casos | B12: Los 10 casos de verificación (RF-09, RF-10, RF-11).
A13: Sensibilidad | B13: Prueba de precio para un caso (RF-10).
A14: Paises · Productos · Rutas · Aranceles · Demanda | B14: Muestra de datos (RF-06).
A15: Parametros · Fuentes · Backlog | B15: Configuración, referencias y avance del sprint.

Sheet Casos
A1: Casos de verificación
A2: Columnas A–I: decisión del equipo. Las columnas J–Q (datos consultados) están agrupadas: use el botón + para verlas.
A4: Caso | B4: ISO | C4: Producto | D4: Transporte | E4: Volumen | F4: Precio (USD) | G4: Equipos | H4: Variación TC | I4: Capital | J4: FOB unit. | K4: Peso kg | L4: Flete/kg | M4: % seguro | N4: % arancel | O4: TC base | P4: Precio ref. | Q4: Demanda | R4: Valor FOB | S4: Flete | T4: Seguro | U4: Valor CIF | V4: Arancel | W4: Costo total | X4: TC aplicado | Y4: Costo en moneda destino | Z4: Índice de precio | AA4: Unidades vendidas | AB4: Ventas | AC4: Utilidad | AD4: Capital final | AE4: ¿Válida? | AF4: Explicación | AG4: Mercado / producto
A5: C01 | B5: USA | C5: P01 | D5: Marítimo | E5: 2000 | F5: 13.87 | G5: 2 | H5: 0 | I5: =Parametros!$B$5 -> 50000 | J5: =INDEX(Productos!$F:$F,MATCH(C5,Productos!$A:$A,0)) -> 8.36 | K5: =INDEX(Productos!$E:$E,MATCH(C5,Productos!$A:$A,0)) -> 18.14 | L5: =INDEX(Rutas!$E:$E,MATCH(B5&"|"&D5,Rutas!$A:$A,0)) -> 0.18 | M5: =INDEX(Rutas!$F:$F,MATCH(B5&"|"&D5,Rutas!$A:$A,0)) -> 0.005 | N5: =INDEX(Aranceles!$F:$F,MATCH(B5&"|"&C5,Aranceles!$A:$A,0)) -> 0 | O5: =INDEX(Paises!$E:$E,MATCH(B5,Paises!$A:$A,0)) -> 1 | P5: =INDEX(Demanda!$F:$F,MATCH(B5&"|"&C5,Demanda!$A:$A,0)) -> 14.6 | Q5: =INDEX(Demanda!$G:$G,MATCH(B5&"|"&C5,Demanda!$A:$A,0)) -> 4000 | R5: =ROUND(E5*J5,2) -> 16720 | S5: =ROUND(E5*K5*L5,2) -> 6530.4 | T5: =ROUND((R5+S5)*M5,2) -> 116.25 | U5: =ROUND(R5+S5+T5,2) -> 23366.65 | V5: =ROUND(U5*N5,2) -> 0 | W5: =ROUND(U5+V5,2) -> 23366.65 | X5: =ROUND(O5*(1+H5),4) -> 1 | Y5: =ROUND(W5*X5,2) -> 23366.65 | Z5: =ROUND((F5/P5)*(1+H5),4) -> 0.95 | AA5: =MIN(E5,ROUNDDOWN((Q5/G5)*Z5^(-Parametros!$B$6),0)) -> 2000 | AB5: =ROUND(AA5*F5,2) -> 27740 | AC5: =ROUND(AB5-W5,2) -> 4373.35 | AD5: =ROUND(I5+AC5,2) -> 54373.35 | AE5: =IF(W5<=I5,"Sí","No: excede el capital") -> Sí | AF5: =IF(AA5<E5,"Vendiste "&AA5&" de "&E5&" unidades. ","Vendiste las "&E5&" unidades enviadas. ")&IF(ABS(Z5-1)<0.005,"Tu precio en moneda local quedó igual al de referencia","Tu precio en moneda local quedó "&ROUND(ABS(Z5-1)*100,0)&" % "&IF(Z5>1,"por encima","por debajo")&" del de referencia")&IF(G5>1," y competiste con "&(G5-1)&" equipo(s) más. "," y no tuviste competencia en ese mercado. ")&IF(V5>0,"El arancel se llevó el "&ROUND(V5/W5*100,0)&" % de tu costo total. ","Este mercado no cobra arancel a tu producto. ")&IF(AC5<0,"Resultado: pérdida.","Resultado: utilidad.") -> Vendiste las 2000 unidades enviadas. Tu precio en moneda local quedó 5 % por debajo del de referencia y competiste con 1 equipo(s) más. Este mercado no cobra arancel a tu producto. Resultado: utilidad. | AG5: =INDEX(Paises!$B:$B,MATCH(B5,Paises!$A:$A,0))&" / "&INDEX(Productos!$B:$B,MATCH(C5,Productos!$A:$A,0)) -> Estados Unidos / Banano
A6: C02 | B6: NLD | C6: P02 | D6: Marítimo | E6: 1500 | F6: 10.92 | G6: 3 | H6: 0 | I6: =Parametros!$B$5 -> 50000 | J6: =INDEX(Productos!$F:$F,MATCH(C6,Productos!$A:$A,0)) -> 6.55 | K6: =INDEX(Productos!$E:$E,MATCH(C6,Productos!$A:$A,0)) -> 12 | L6: =INDEX(Rutas!$E:$E,MATCH(B6&"|"&D6,Rutas!$A:$A,0)) -> 0.19 | M6: =INDEX(Rutas!$F:$F,MATCH(B6&"|"&D6,Rutas!$A:$A,0)) -> 0.005 | N6: =INDEX(Aranceles!$F:$F,MATCH(B6&"|"&C6,Aranceles!$A:$A,0)) -> 0.058 | O6: =INDEX(Paises!$E:$E,MATCH(B6,Paises!$A:$A,0)) -> 0.8692 | P6: =INDEX(Demanda!$F:$F,MATCH(B6&"|"&C6,Demanda!$A:$A,0)) -> 11.74 | Q6: =INDEX(Demanda!$G:$G,MATCH(B6&"|"&C6,Demanda!$A:$A,0)) -> 4500 | R6: =ROUND(E6*J6,2) -> 9825 | S6: =ROUND(E6*K6*L6,2) -> 3420 | T6: =ROUND((R6+S6)*M6,2) -> 66.23 | U6: =ROUND(R6+S6+T6,2) -> 13311.23 | V6: =ROUND(U6*N6,2) -> 772.05 | W6: =ROUND(U6+V6,2) -> 14083.28 | X6: =ROUND(O6*(1+H6),4) -> 0.8692 | Y6: =ROUND(W6*X6,2) -> 12241.19 | Z6: =ROUND((F6/P6)*(1+H6),4) -> 0.9302 | AA6: =MIN(E6,ROUNDDOWN((Q6/G6)*Z6^(-Parametros!$B$6),0)) -> 1500 | AB6: =ROUND(AA6*F6,2) -> 16380 | AC6: =ROUND(AB6-W6,2) -> 2296.72 | AD6: =ROUND(I6+AC6,2) -> 52296.72 | AE6: =IF(W6<=I6,"Sí","No: excede el capital") -> Sí | AF6: =IF(AA6<E6,"Vendiste "&AA6&" de "&E6&" unidades. ","Vendiste las "&E6&" unidades enviadas. ")&IF(ABS(Z6-1)<0.005,"Tu precio en moneda local quedó igual al de referencia","Tu precio en moneda local quedó "&ROUND(ABS(Z6-1)*100,0)&" % "&IF(Z6>1,"por encima","por debajo")&" del de referencia")&IF(G6>1," y competiste con "&(G6-1)&" equipo(s) más. "," y no tuviste competencia en ese mercado. ")&IF(V6>0,"El arancel se llevó el "&ROUND(V6/W6*100,0)&" % de tu costo total. ","Este mercado no cobra arancel a tu producto. ")&IF(AC6<0,"Resultado: pérdida.","Resultado: utilidad.") -> Vendiste las 1500 unidades enviadas. Tu precio en moneda local quedó 7 % por debajo del de referencia y competiste con 2 equipo(s) más. El arancel se llevó el 5 % de tu costo total. Resultado: utilidad. | AG6: =INDEX(Paises!$B:$B,MATCH(B6,Paises!$A:$A,0))&" / "&INDEX(Productos!$B:$B,MATCH(C6,Productos!$A:$A,0)) -> Países Bajos / Piña
A7: C03 | B7: DEU | C7: P03 | D7: Marítimo | E7: 40 | F7: 346.78 | G7: 2 | H7: 0 | I7: =Parametros!$B$5 -> 50000 | J7: =INDEX(Productos!$F:$F,MATCH(C7,Productos!$A:$A,0)) -> 281.83 | K7: =INDEX(Productos!$E:$E,MATCH(C7,Productos!$A:$A,0)) -> 46 | L7: =INDEX(Rutas!$E:$E,MATCH(B7&"|"&D7,Rutas!$A:$A,0)) -> 0.19 | M7: =INDEX(Rutas!$F:$F,MATCH(B7&"|"&D7,Rutas!$A:$A,0)) -> 0.005 | N7: =INDEX(Aranceles!$F:$F,MATCH(B7&"|"&C7,Aranceles!$A:$A,0)) -> 0 | O7: =INDEX(Paises!$E:$E,MATCH(B7,Paises!$A:$A,0)) -> 0.8692 | P7: =INDEX(Demanda!$F:$F,MATCH(B7&"|"&C7,Demanda!$A:$A,0)) -> 365.03 | Q7: =INDEX(Demanda!$G:$G,MATCH(B7&"|"&C7,Demanda!$A:$A,0)) -> 90 | R7: =ROUND(E7*J7,2) -> 11273.2 | S7: =ROUND(E7*K7*L7,2) -> 349.6 | T7: =ROUND((R7+S7)*M7,2) -> 58.11 | U7: =ROUND(R7+S7+T7,2) -> 11680.91 | V7: =ROUND(U7*N7,2) -> 0 | W7: =ROUND(U7+V7,2) -> 11680.91 | X7: =ROUND(O7*(1+H7),4) -> 0.8692 | Y7: =ROUND(W7*X7,2) -> 10153.05 | Z7: =ROUND((F7/P7)*(1+H7),4) -> 0.95 | AA7: =MIN(E7,ROUNDDOWN((Q7/G7)*Z7^(-Parametros!$B$6),0)) -> 40 | AB7: =ROUND(AA7*F7,2) -> 13871.2 | AC7: =ROUND(AB7-W7,2) -> 2190.29 | AD7: =ROUND(I7+AC7,2) -> 52190.29 | AE7: =IF(W7<=I7,"Sí","No: excede el capital") -> Sí | AF7: =IF(AA7<E7,"Vendiste "&AA7&" de "&E7&" unidades. ","Vendiste las "&E7&" unidades enviadas. ")&IF(ABS(Z7-1)<0.005,"Tu precio en moneda local quedó igual al de referencia","Tu precio en moneda local quedó "&ROUND(ABS(Z7-1)*100,0)&" % "&IF(Z7>1,"por encima","por debajo")&" del de referencia")&IF(G7>1," y competiste con "&(G7-1)&" equipo(s) más. "," y no tuviste competencia en ese mercado. ")&IF(V7>0,"El arancel se llevó el "&ROUND(V7/W7*100,0)&" % de tu costo total. ","Este mercado no cobra arancel a tu producto. ")&IF(AC7<0,"Resultado: pérdida.","Resultado: utilidad.") -> Vendiste las 40 unidades enviadas. Tu precio en moneda local quedó 5 % por debajo del de referencia y competiste con 1 equipo(s) más. Este mercado no cobra arancel a tu producto. Resultado: utilidad. | AG7: =INDEX(Paises!$B:$B,MATCH(B7,Paises!$A:$A,0))&" / "&INDEX(Productos!$B:$B,MATCH(C7,Productos!$A:$A,0)) -> Alemania / Café oro (verde)
A8: C04 | B8: JPN | C8: P04 | D8: Aéreo | E8: 100 | F8: 180.71 | G8: 2 | H8: 0.04 | I8: =Parametros!$B$5 -> 50000 | J8: =INDEX(Productos!$F:$F,MATCH(C8,Productos!$A:$A,0)) -> 116.56 | K8: =INDEX(Productos!$E:$E,MATCH(C8,Productos!$A:$A,0)) -> 12 | L8: =INDEX(Rutas!$E:$E,MATCH(B8&"|"&D8,Rutas!$A:$A,0)) -> 3.9 | M8: =INDEX(Rutas!$F:$F,MATCH(B8&"|"&D8,Rutas!$A:$A,0)) -> 0.0035 | N8: =INDEX(Aranceles!$F:$F,MATCH(B8&"|"&C8,Aranceles!$A:$A,0)) -> 0.12 | O8: =INDEX(Paises!$E:$E,MATCH(B8,Paises!$A:$A,0)) -> 156.4171 | P8: =INDEX(Demanda!$F:$F,MATCH(B8&"|"&C8,Demanda!$A:$A,0)) -> 172.1 | Q8: =INDEX(Demanda!$G:$G,MATCH(B8&"|"&C8,Demanda!$A:$A,0)) -> 150 | R8: =ROUND(E8*J8,2) -> 11656 | S8: =ROUND(E8*K8*L8,2) -> 4680 | T8: =ROUND((R8+S8)*M8,2) -> 57.18 | U8: =ROUND(R8+S8+T8,2) -> 16393.18 | V8: =ROUND(U8*N8,2) -> 1967.18 | W8: =ROUND(U8+V8,2) -> 18360.36 | X8: =ROUND(O8*(1+H8),4) -> 162.6738 | Y8: =ROUND(W8*X8,2) -> 2986749.5 | Z8: =ROUND((F8/P8)*(1+H8),4) -> 1.092 | AA8: =MIN(E8,ROUNDDOWN((Q8/G8)*Z8^(-Parametros!$B$6),0)) -> 65 | AB8: =ROUND(AA8*F8,2) -> 11746.15 | AC8: =ROUND(AB8-W8,2) -> -6614.21 | AD8: =ROUND(I8+AC8,2) -> 43385.79 | AE8: =IF(W8<=I8,"Sí","No: excede el capital") -> Sí | AF8: =IF(AA8<E8,"Vendiste "&AA8&" de "&E8&" unidades. ","Vendiste las "&E8&" unidades enviadas. ")&IF(ABS(Z8-1)<0.005,"Tu precio en moneda local quedó igual al de referencia","Tu precio en moneda local quedó "&ROUND(ABS(Z8-1)*100,0)&" % "&IF(Z8>1,"por encima","por debajo")&" del de referencia")&IF(G8>1," y competiste con "&(G8-1)&" equipo(s) más. "," y no tuviste competencia en ese mercado. ")&IF(V8>0,"El arancel se llevó el "&ROUND(V8/W8*100,0)&" % de tu costo total. ","Este mercado no cobra arancel a tu producto. ")&IF(AC8<0,"Resultado: pérdida.","Resultado: utilidad.") -> Vendiste 65 de 100 unidades. Tu precio en moneda local quedó 9 % por encima del de referencia y competiste con 1 equipo(s) más. El arancel se llevó el 11 % de tu costo total. Resultado: pérdida. | AG8: =INDEX(Paises!$B:$B,MATCH(B8,Paises!$A:$A,0))&" / "&INDEX(Productos!$B:$B,MATCH(C8,Productos!$A:$A,0)) -> Japón / Café tostado
A9: C05 | B9: GBR | C9: P05 | D9: Marítimo | E9: 1200 | F9: 17.98 | G9: 3 | H9: 0 | I9: =Parametros!$B$5 -> 50000 | J9: =INDEX(Productos!$F:$F,MATCH(C9,Productos!$A:$A,0)) -> 11.1 | K9: =INDEX(Productos!$E:$E,MATCH(C9,Productos!$A:$A,0)) -> 15 | L9: =INDEX(Rutas!$E:$E,MATCH(B9&"|"&D9,Rutas!$A:$A,0)) -> 0.19 | M9: =INDEX(Rutas!$F:$F,MATCH(B9&"|"&D9,Rutas!$A:$A,0)) -> 0.005 | N9: =INDEX(Aranceles!$F:$F,MATCH(B9&"|"&C9,Aranceles!$A:$A,0)) -> 0.08 | O9: =INDEX(Paises!$E:$E,MATCH(B9,Paises!$A:$A,0)) -> 0.7459 | P9: =INDEX(Demanda!$F:$F,MATCH(B9&"|"&C9,Demanda!$A:$A,0)) -> 18.93 | Q9: =INDEX(Demanda!$G:$G,MATCH(B9&"|"&C9,Demanda!$A:$A,0)) -> 3600 | R9: =ROUND(E9*J9,2) -> 13320 | S9: =ROUND(E9*K9*L9,2) -> 3420 | T9: =ROUND((R9+S9)*M9,2) -> 83.7 | U9: =ROUND(R9+S9+T9,2) -> 16823.7 | V9: =ROUND(U9*N9,2) -> 1345.9 | W9: =ROUND(U9+V9,2) -> 18169.6 | X9: =ROUND(O9*(1+H9),4) -> 0.7459 | Y9: =ROUND(W9*X9,2) -> 13552.7 | Z9: =ROUND((F9/P9)*(1+H9),4) -> 0.9498 | AA9: =MIN(E9,ROUNDDOWN((Q9/G9)*Z9^(-Parametros!$B$6),0)) -> 1200 | AB9: =ROUND(AA9*F9,2) -> 21576 | AC9: =ROUND(AB9-W9,2) -> 3406.4 | AD9: =ROUND(I9+AC9,2) -> 53406.4 | AE9: =IF(W9<=I9,"Sí","No: excede el capital") -> Sí | AF9: =IF(AA9<E9,"Vendiste "&AA9&" de "&E9&" unidades. ","Vendiste las "&E9&" unidades enviadas. ")&IF(ABS(Z9-1)<0.005,"Tu precio en moneda local quedó igual al de referencia","Tu precio en moneda local quedó "&ROUND(ABS(Z9-1)*100,0)&" % "&IF(Z9>1,"por encima","por debajo")&" del de referencia")&IF(G9>1," y competiste con "&(G9-1)&" equipo(s) más. "," y no tuviste competencia en ese mercado. ")&IF(V9>0,"El arancel se llevó el "&ROUND(V9/W9*100,0)&" % de tu costo total. ","Este mercado no cobra arancel a tu producto. ")&IF(AC9<0,"Resultado: pérdida.","Resultado: utilidad.") -> Vendiste las 1200 unidades enviadas. Tu precio en moneda local quedó 5 % por debajo del de referencia y competiste con 2 equipo(s) más. El arancel se llevó el 7 % de tu costo total. Resultado: utilidad. | AG9: =INDEX(Paises!$B:$B,MATCH(B9,Paises!$A:$A,0))&" / "&INDEX(Productos!$B:$B,MATCH(C9,Productos!$A:$A,0)) -> Reino Unido / Melón
A10: C06 | B10: CAN | C10: P06 | D10: Aéreo | E10: 800 | F10: 9.18 | G10: 2 | H10: 0 | I10: =Parametros!$B$5 -> 50000 | J10: =INDEX(Productos!$F:$F,MATCH(C10,Productos!$A:$A,0)) -> 5.5 | K10: =INDEX(Productos!$E:$E,MATCH(C10,Productos!$A:$A,0)) -> 4 | L10: =INDEX(Rutas!$E:$E,MATCH(B10&"|"&D10,Rutas!$A:$A,0)) -> 2.2 | M10: =INDEX(Rutas!$F:$F,MATCH(B10&"|"&D10,Rutas!$A:$A,0)) -> 0.0035 | N10: =INDEX(Aranceles!$F:$F,MATCH(B10&"|"&C10,Aranceles!$A:$A,0)) -> 0 | O10: =INDEX(Paises!$E:$E,MATCH(B10,Paises!$A:$A,0)) -> 1.3972 | P10: =INDEX(Demanda!$F:$F,MATCH(B10&"|"&C10,Demanda!$A:$A,0)) -> 8.42 | Q10: =INDEX(Demanda!$G:$G,MATCH(B10&"|"&C10,Demanda!$A:$A,0)) -> 1000 | R10: =ROUND(E10*J10,2) -> 4400 | S10: =ROUND(E10*K10*L10,2) -> 7040 | T10: =ROUND((R10+S10)*M10,2) -> 40.04 | U10: =ROUND(R10+S10+T10,2) -> 11480.04 | V10: =ROUND(U10*N10,2) -> 0 | W10: =ROUND(U10+V10,2) -> 11480.04 | X10: =ROUND(O10*(1+H10),4) -> 1.3972 | Y10: =ROUND(W10*X10,2) -> 16039.91 | Z10: =ROUND((F10/P10)*(1+H10),4) -> 1.0903 | AA10: =MIN(E10,ROUNDDOWN((Q10/G10)*Z10^(-Parametros!$B$6),0)) -> 439 | AB10: =ROUND(AA10*F10,2) -> 4030.02 | AC10: =ROUND(AB10-W10,2) -> -7450.02 | AD10: =ROUND(I10+AC10,2) -> 42549.98 | AE10: =IF(W10<=I10,"Sí","No: excede el capital") -> Sí | AF10: =IF(AA10<E10,"Vendiste "&AA10&" de "&E10&" unidades. ","Vendiste las "&E10&" unidades enviadas. ")&IF(ABS(Z10-1)<0.005,"Tu precio en moneda local quedó igual al de referencia","Tu precio en moneda local quedó "&ROUND(ABS(Z10-1)*100,0)&" % "&IF(Z10>1,"por encima","por debajo")&" del de referencia")&IF(G10>1," y competiste con "&(G10-1)&" equipo(s) más. "," y no tuviste competencia en ese mercado. ")&IF(V10>0,"El arancel se llevó el "&ROUND(V10/W10*100,0)&" % de tu costo total. ","Este mercado no cobra arancel a tu producto. ")&IF(AC10<0,"Resultado: pérdida.","Resultado: utilidad.") -> Vendiste 439 de 800 unidades. Tu precio en moneda local quedó 9 % por encima del de referencia y competiste con 1 equipo(s) más. Este mercado no cobra arancel a tu producto. Resultado: pérdida. | AG10: =INDEX(Paises!$B:$B,MATCH(B10,Paises!$A:$A,0))&" / "&INDEX(Productos!$B:$B,MATCH(C10,Productos!$A:$A,0)) -> Canadá / Mango
A11: C07 | B11: USA | C11: P07 | D11: Marítimo | E11: 900 | F11: 33.34 | G11: 2 | H11: 0 | I11: =Parametros!$B$5 -> 50000 | J11: =INDEX(Productos!$F:$F,MATCH(C11,Productos!$A:$A,0)) -> 19.47 | K11: =INDEX(Productos!$E:$E,MATCH(C11,Productos!$A:$A,0)) -> 18 | L11: =INDEX(Rutas!$E:$E,MATCH(B11&"|"&D11,Rutas!$A:$A,0)) -> 0.18 | M11: =INDEX(Rutas!$F:$F,MATCH(B11&"|"&D11,Rutas!$A:$A,0)) -> 0.005 | N11: =INDEX(Aranceles!$F:$F,MATCH(B11&"|"&C11,Aranceles!$A:$A,0)) -> 0.113 | O11: =INDEX(Paises!$E:$E,MATCH(B11,Paises!$A:$A,0)) -> 1 | P11: =INDEX(Demanda!$F:$F,MATCH(B11&"|"&C11,Demanda!$A:$A,0)) -> 31.75 | Q11: =INDEX(Demanda!$G:$G,MATCH(B11&"|"&C11,Demanda!$A:$A,0)) -> 1200 | R11: =ROUND(E11*J11,2) -> 17523 | S11: =ROUND(E11*K11*L11,2) -> 2916 | T11: =ROUND((R11+S11)*M11,2) -> 102.2 | U11: =ROUND(R11+S11+T11,2) -> 20541.2 | V11: =ROUND(U11*N11,2) -> 2321.16 | W11: =ROUND(U11+V11,2) -> 22862.36 | X11: =ROUND(O11*(1+H11),4) -> 1 | Y11: =ROUND(W11*X11,2) -> 22862.36 | Z11: =ROUND((F11/P11)*(1+H11),4) -> 1.0501 | AA11: =MIN(E11,ROUNDDOWN((Q11/G11)*Z11^(-Parametros!$B$6),0)) -> 557 | AB11: =ROUND(AA11*F11,2) -> 18570.38 | AC11: =ROUND(AB11-W11,2) -> -4291.98 | AD11: =ROUND(I11+AC11,2) -> 45708.02 | AE11: =IF(W11<=I11,"Sí","No: excede el capital") -> Sí | AF11: =IF(AA11<E11,"Vendiste "&AA11&" de "&E11&" unidades. ","Vendiste las "&E11&" unidades enviadas. ")&IF(ABS(Z11-1)<0.005,"Tu precio en moneda local quedó igual al de referencia","Tu precio en moneda local quedó "&ROUND(ABS(Z11-1)*100,0)&" % "&IF(Z11>1,"por encima","por debajo")&" del de referencia")&IF(G11>1," y competiste con "&(G11-1)&" equipo(s) más. "," y no tuviste competencia en ese mercado. ")&IF(V11>0,"El arancel se llevó el "&ROUND(V11/W11*100,0)&" % de tu costo total. ","Este mercado no cobra arancel a tu producto. ")&IF(AC11<0,"Resultado: pérdida.","Resultado: utilidad.") -> Vendiste 557 de 900 unidades. Tu precio en moneda local quedó 5 % por encima del de referencia y competiste con 1 equipo(s) más. El arancel se llevó el 10 % de tu costo total. Resultado: pérdida. | AG11: =INDEX(Paises!$B:$B,MATCH(B11,Paises!$A:$A,0))&" / "&INDEX(Productos!$B:$B,MATCH(C11,Productos!$A:$A,0)) -> Estados Unidos / Yuca
A12: C08 | B12: ESP | C12: P09 | D12: Aéreo | E12: 200 | F12: 69.47 | G12: 2 | H12: -0.03 | I12: =Parametros!$B$5 -> 50000 | J12: =INDEX(Productos!$F:$F,MATCH(C12,Productos!$A:$A,0)) -> 25 | K12: =INDEX(Productos!$E:$E,MATCH(C12,Productos!$A:$A,0)) -> 10 | L12: =INDEX(Rutas!$E:$E,MATCH(B12&"|"&D12,Rutas!$A:$A,0)) -> 2.7 | M12: =INDEX(Rutas!$F:$F,MATCH(B12&"|"&D12,Rutas!$A:$A,0)) -> 0.0035 | N12: =INDEX(Aranceles!$F:$F,MATCH(B12&"|"&C12,Aranceles!$A:$A,0)) -> 0.065 | O12: =INDEX(Paises!$E:$E,MATCH(B12,Paises!$A:$A,0)) -> 0.8692 | P12: =INDEX(Demanda!$F:$F,MATCH(B12&"|"&C12,Demanda!$A:$A,0)) -> 69.47 | Q12: =INDEX(Demanda!$G:$G,MATCH(B12&"|"&C12,Demanda!$A:$A,0)) -> 400 | R12: =ROUND(E12*J12,2) -> 5000 | S12: =ROUND(E12*K12*L12,2) -> 5400 | T12: =ROUND((R12+S12)*M12,2) -> 36.4 | U12: =ROUND(R12+S12+T12,2) -> 10436.4 | V12: =ROUND(U12*N12,2) -> 678.37 | W12: =ROUND(U12+V12,2) -> 11114.77 | X12: =ROUND(O12*(1+H12),4) -> 0.8431 | Y12: =ROUND(W12*X12,2) -> 9370.86 | Z12: =ROUND((F12/P12)*(1+H12),4) -> 0.97 | AA12: =MIN(E12,ROUNDDOWN((Q12/G12)*Z12^(-Parametros!$B$6),0)) -> 200 | AB12: =ROUND(AA12*F12,2) -> 13894 | AC12: =ROUND(AB12-W12,2) -> 2779.23 | AD12: =ROUND(I12+AC12,2) -> 52779.23 | AE12: =IF(W12<=I12,"Sí","No: excede el capital") -> Sí | AF12: =IF(AA12<E12,"Vendiste "&AA12&" de "&E12&" unidades. ","Vendiste las "&E12&" unidades enviadas. ")&IF(ABS(Z12-1)<0.005,"Tu precio en moneda local quedó igual al de referencia","Tu precio en moneda local quedó "&ROUND(ABS(Z12-1)*100,0)&" % "&IF(Z12>1,"por encima","por debajo")&" del de referencia")&IF(G12>1," y competiste con "&(G12-1)&" equipo(s) más. "," y no tuviste competencia en ese mercado. ")&IF(V12>0,"El arancel se llevó el "&ROUND(V12/W12*100,0)&" % de tu costo total. ","Este mercado no cobra arancel a tu producto. ")&IF(AC12<0,"Resultado: pérdida.","Resultado: utilidad.") -> Vendiste las 200 unidades enviadas. Tu precio en moneda local quedó 3 % por debajo del de referencia y competiste con 1 equipo(s) más. El arancel se llevó el 6 % de tu costo total. Resultado: utilidad. | AG12: =INDEX(Paises!$B:$B,MATCH(B12,Paises!$A:$A,0))&" / "&INDEX(Productos!$B:$B,MATCH(C12,Productos!$A:$A,0)) -> España / Plantas ornamentales
A13: C09 | B13: MEX | C13: P15 | D13: Aéreo | E13: 60 | F13: 553.4 | G13: 2 | H13: 0.06 | I13: =Parametros!$B$5 -> 50000 | J13: =INDEX(Productos!$F:$F,MATCH(C13,Productos!$A:$A,0)) -> 450 | K13: =INDEX(Productos!$E:$E,MATCH(C13,Productos!$A:$A,0)) -> 8 | L13: =INDEX(Rutas!$E:$E,MATCH(B13&"|"&D13,Rutas!$A:$A,0)) -> 1.8 | M13: =INDEX(Rutas!$F:$F,MATCH(B13&"|"&D13,Rutas!$A:$A,0)) -> 0.0035 | N13: =INDEX(Aranceles!$F:$F,MATCH(B13&"|"&C13,Aranceles!$A:$A,0)) -> 0 | O13: =INDEX(Paises!$E:$E,MATCH(B13,Paises!$A:$A,0)) -> 17.2695 | P13: =INDEX(Demanda!$F:$F,MATCH(B13&"|"&C13,Demanda!$A:$A,0)) -> 582.53 | Q13: =INDEX(Demanda!$G:$G,MATCH(B13&"|"&C13,Demanda!$A:$A,0)) -> 100 | R13: =ROUND(E13*J13,2) -> 27000 | S13: =ROUND(E13*K13*L13,2) -> 864 | T13: =ROUND((R13+S13)*M13,2) -> 97.52 | U13: =ROUND(R13+S13+T13,2) -> 27961.52 | V13: =ROUND(U13*N13,2) -> 0 | W13: =ROUND(U13+V13,2) -> 27961.52 | X13: =ROUND(O13*(1+H13),4) -> 18.3057 | Y13: =ROUND(W13*X13,2) -> 511855.2 | Z13: =ROUND((F13/P13)*(1+H13),4) -> 1.007 | AA13: =MIN(E13,ROUNDDOWN((Q13/G13)*Z13^(-Parametros!$B$6),0)) -> 49 | AB13: =ROUND(AA13*F13,2) -> 27116.6 | AC13: =ROUND(AB13-W13,2) -> -844.92 | AD13: =ROUND(I13+AC13,2) -> 49155.08 | AE13: =IF(W13<=I13,"Sí","No: excede el capital") -> Sí | AF13: =IF(AA13<E13,"Vendiste "&AA13&" de "&E13&" unidades. ","Vendiste las "&E13&" unidades enviadas. ")&IF(ABS(Z13-1)<0.005,"Tu precio en moneda local quedó igual al de referencia","Tu precio en moneda local quedó "&ROUND(ABS(Z13-1)*100,0)&" % "&IF(Z13>1,"por encima","por debajo")&" del de referencia")&IF(G13>1," y competiste con "&(G13-1)&" equipo(s) más. "," y no tuviste competencia en ese mercado. ")&IF(V13>0,"El arancel se llevó el "&ROUND(V13/W13*100,0)&" % de tu costo total. ","Este mercado no cobra arancel a tu producto. ")&IF(AC13<0,"Resultado: pérdida.","Resultado: utilidad.") -> Vendiste 49 de 60 unidades. Tu precio en moneda local quedó 1 % por encima del de referencia y competiste con 1 equipo(s) más. Este mercado no cobra arancel a tu producto. Resultado: pérdida. | AG13: =INDEX(Paises!$B:$B,MATCH(B13,Paises!$A:$A,0))&" / "&INDEX(Productos!$B:$B,MATCH(C13,Productos!$A:$A,0)) -> México / Dispositivos médicos (catéteres)
A14: C10 | B14: CHN | C14: P12 | D14: Marítimo | E14: 40 | F14: 531.59 | G14: 2 | H14: 0 | I14: =Parametros!$B$5 -> 50000 | J14: =INDEX(Productos!$F:$F,MATCH(C14,Productos!$A:$A,0)) -> 275 | K14: =INDEX(Productos!$E:$E,MATCH(C14,Productos!$A:$A,0)) -> 250 | L14: =INDEX(Rutas!$E:$E,MATCH(B14&"|"&D14,Rutas!$A:$A,0)) -> 0.45 | M14: =INDEX(Rutas!$F:$F,MATCH(B14&"|"&D14,Rutas!$A:$A,0)) -> 0.005 | N14: =INDEX(Aranceles!$F:$F,MATCH(B14&"|"&C14,Aranceles!$A:$A,0)) -> 0.05 | O14: =INDEX(Paises!$E:$E,MATCH(B14,Paises!$A:$A,0)) -> 6.7084 | P14: =INDEX(Demanda!$F:$F,MATCH(B14&"|"&C14,Demanda!$A:$A,0)) -> 511.14 | Q14: =INDEX(Demanda!$G:$G,MATCH(B14&"|"&C14,Demanda!$A:$A,0)) -> 60 | R14: =ROUND(E14*J14,2) -> 11000 | S14: =ROUND(E14*K14*L14,2) -> 4500 | T14: =ROUND((R14+S14)*M14,2) -> 77.5 | U14: =ROUND(R14+S14+T14,2) -> 15577.5 | V14: =ROUND(U14*N14,2) -> 778.88 | W14: =ROUND(U14+V14,2) -> 16356.38 | X14: =ROUND(O14*(1+H14),4) -> 6.7084 | Y14: =ROUND(W14*X14,2) -> 109725.14 | Z14: =ROUND((F14/P14)*(1+H14),4) -> 1.04 | AA14: =MIN(E14,ROUNDDOWN((Q14/G14)*Z14^(-Parametros!$B$6),0)) -> 28 | AB14: =ROUND(AA14*F14,2) -> 14884.52 | AC14: =ROUND(AB14-W14,2) -> -1471.86 | AD14: =ROUND(I14+AC14,2) -> 48528.14 | AE14: =IF(W14<=I14,"Sí","No: excede el capital") -> Sí | AF14: =IF(AA14<E14,"Vendiste "&AA14&" de "&E14&" unidades. ","Vendiste las "&E14&" unidades enviadas. ")&IF(ABS(Z14-1)<0.005,"Tu precio en moneda local quedó igual al de referencia","Tu precio en moneda local quedó "&ROUND(ABS(Z14-1)*100,0)&" % "&IF(Z14>1,"por encima","por debajo")&" del de referencia")&IF(G14>1," y competiste con "&(G14-1)&" equipo(s) más. "," y no tuviste competencia en ese mercado. ")&IF(V14>0,"El arancel se llevó el "&ROUND(V14/W14*100,0)&" % de tu costo total. ","Este mercado no cobra arancel a tu producto. ")&IF(AC14<0,"Resultado: pérdida.","Resultado: utilidad.") -> Vendiste 28 de 40 unidades. Tu precio en moneda local quedó 4 % por encima del de referencia y competiste con 1 equipo(s) más. El arancel se llevó el 5 % de tu costo total. Resultado: pérdida. | AG14: =INDEX(Paises!$B:$B,MATCH(B14,Paises!$A:$A,0))&" / "&INDEX(Productos!$B:$B,MATCH(C14,Productos!$A:$A,0)) -> China / Jugo concentrado de piña
A15: Total | R15: =SUM(R5:R14) -> 127717.2 | S15: =SUM(S5:S14) -> 39120 | T15: =SUM(T5:T14) -> 735.13 | U15: =SUM(U5:U14) -> 167572.33 | V15: =SUM(V5:V14) -> 7863.54 | W15: =SUM(W5:W14) -> 175435.87 | AB15: =SUM(AB5:AB14) -> 169808.87 | AC15: =SUM(AC5:AC14) -> -5627
A17: C04 reproduce el ejemplo del documento: arancel de 12 % y la moneda destino pierde 4 % de valor.

Sheet Sensibilidad
A1: Prueba de precio (RF-10)
A2: Elija un caso en B4. La tabla muestra la utilidad con distintos precios y el mismo volumen.
A4: Caso | B4: C01
A5: Fila en Casos | B5: =MATCH(B4,Casos!$A:$A,0) -> 5
A6: Volumen | B6: =INDEX(Casos!$E:$E,$B$5) -> 2000
A7: Costo total | B7: =INDEX(Casos!$W:$W,$B$5) -> 23366.65
A8: Precio de referencia | B8: =INDEX(Casos!$P:$P,$B$5) -> 14.6
A9: Demanda por equipo | B9: =INDEX(Casos!$Q:$Q,$B$5)/INDEX(Casos!$G:$G,$B$5) -> 2000
A10: Variación TC | B10: =INDEX(Casos!$H:$H,$B$5) -> 0
A12: Precio vs. referencia | B12: Precio | C12: Índice | D12: Unidades vendidas | E12: Ventas | F12: Utilidad
A13: 0.7 | B13: =ROUND($B$8*A13,2) -> 10.22 | C13: =ROUND((B13/$B$8)*(1+$B$10),4) -> 0.7 | D13: =MIN($B$6,ROUNDDOWN($B$9*C13^(-Parametros!$B$6),0)) -> 2000 | E13: =ROUND(D13*B13,2) -> 20440 | F13: =ROUND(E13-$B$7,2) -> -2926.65
A14: 0.8 | B14: =ROUND($B$8*A14,2) -> 11.68 | C14: =ROUND((B14/$B$8)*(1+$B$10),4) -> 0.8 | D14: =MIN($B$6,ROUNDDOWN($B$9*C14^(-Parametros!$B$6),0)) -> 2000 | E14: =ROUND(D14*B14,2) -> 23360 | F14: =ROUND(E14-$B$7,2) -> -6.65
A15: 0.9 | B15: =ROUND($B$8*A15,2) -> 13.14 | C15: =ROUND((B15/$B$8)*(1+$B$10),4) -> 0.9 | D15: =MIN($B$6,ROUNDDOWN($B$9*C15^(-Parametros!$B$6),0)) -> 2000 | E15: =ROUND(D15*B15,2) -> 26280 | F15: =ROUND(E15-$B$7,2) -> 2913.35
A16: 1 | B16: =ROUND($B$8*A16,2) -> 14.6 | C16: =ROUND((B16/$B$8)*(1+$B$10),4) -> 1 | D16: =MIN($B$6,ROUNDDOWN($B$9*C16^(-Parametros!$B$6),0)) -> 2000 | E16: =ROUND(D16*B16,2) -> 29200 | F16: =ROUND(E16-$B$7,2) -> 5833.35
A17: 1.1 | B17: =ROUND($B$8*A17,2) -> 16.06 | C17: =ROUND((B17/$B$8)*(1+$B$10),4) -> 1.1 | D17: =MIN($B$6,ROUNDDOWN($B$9*C17^(-Parametros!$B$6),0)) -> 1733 | E17: =ROUND(D17*B17,2) -> 27831.98 | F17: =ROUND(E17-$B$7,2) -> 4465.33
A18: 1.2 | B18: =ROUND($B$8*A18,2) -> 17.52 | C18: =ROUND((B18/$B$8)*(1+$B$10),4) -> 1.2 | D18: =MIN($B$6,ROUNDDOWN($B$9*C18^(-Parametros!$B$6),0)) -> 1521 | E18: =ROUND(D18*B18,2) -> 26647.92 | F18: =ROUND(E18-$B$7,2) -> 3281.27
A19: 1.3 | B19: =ROUND($B$8*A19,2) -> 18.98 | C19: =ROUND((B19/$B$8)*(1+$B$10),4) -> 1.3 | D19: =MIN($B$6,ROUNDDOWN($B$9*C19^(-Parametros!$B$6),0)) -> 1349 | E19: =ROUND(D19*B19,2) -> 25604.02 | F19: =ROUND(E19-$B$7,2) -> 2237.37

Sheet Paises
A1: Países destino
A2: Tipo de cambio en unidades por 1 USD (promedio de septiembre 2026) y perfil cultural de Hofstede.
A4: ISO | B4: País | C4: Moneda | D4: Código | E4: Unidades por USD | F4: Fuente TC | G4: Fecha de corte | H4: Distancia al poder | I4: Individualismo | J4: Masculinidad | K4: Aversión a la incertidumbre | L4: Largo plazo | M4: Indulgencia | N4: Fuente Hofstede | O4: Estado
A5: USA | B5: Estados Unidos | C5: Dólar estadounidense | D5: USD | E5: 1 | F5: F7 | G5: 2026-09 | H5: 40 | I5: 91 | J5: 62 | K5: 46 | L5: 26 | M5: 68 | N5: F5 | O5: TC verificado (oficial). Hofstede: Verificado (secundaria)
A6: NLD | B6: Países Bajos | C6: Euro | D6: EUR | E6: =ROUND(1/1.1505,4) -> 0.8692 | F6: F7 | G6: 2026-09 | H6: 38 | I6: 80 | J6: 14 | K6: 53 | L6: 67 | M6: 68 | N6: F5 | O6: TC verificado (oficial). Hofstede: PDI–UAI verificado; LTO e IVR: matriz 2010 (referencia)
A7: BEL | B7: Bélgica | C7: Euro | D7: EUR | E7: =ROUND(1/1.1505,4) -> 0.8692 | F7: F7 | G7: 2026-09 | H7: 65 | I7: 75 | J7: 54 | K7: 94 | L7: 82 | M7: 57 | N7: F5 | O7: TC verificado (oficial). Hofstede: PDI–UAI verificado; LTO e IVR: matriz 2010 (referencia)
A8: DEU | B8: Alemania | C8: Euro | D8: EUR | E8: =ROUND(1/1.1505,4) -> 0.8692 | F8: F7 | G8: 2026-09 | H8: 35 | I8: 67 | J8: 66 | K8: 65 | L8: 83 | M8: 40 | N8: F5 | O8: TC verificado (oficial). Hofstede: Verificado (secundaria)
A9: ESP | B9: España | C9: Euro | D9: EUR | E9: =ROUND(1/1.1505,4) -> 0.8692 | F9: F7 | G9: 2026-09 | H9: 57 | I9: 51 | J9: 42 | K9: 86 | L9: 48 | M9: 44 | N9: F5 | O9: TC verificado (oficial). Hofstede: Verificado (secundaria)
A10: GBR | B10: Reino Unido | C10: Libra esterlina | D10: GBP | E10: =ROUND(1/1.3406,4) -> 0.7459 | F10: F7 | G10: 2026-09 | H10: 35 | I10: 89 | J10: 66 | K10: 35 | L10: 51 | M10: 69 | N10: F5 | O10: TC verificado (oficial). Hofstede: Verificado (secundaria)
A11: MEX | B11: México | C11: Peso mexicano | D11: MXN | E11: 17.2695 | F11: F7 | G11: 2026-09 | H11: 81 | I11: 30 | J11: 69 | K11: 82 | L11: 24 | M11: 97 | N11: F5 | O11: TC verificado (oficial). Hofstede: PDI–UAI verificado; LTO e IVR: matriz 2010 (referencia)
A12: CAN | B12: Canadá | C12: Dólar canadiense | D12: CAD | E12: 1.3972 | F12: F7 | G12: 2026-09 | H12: 39 | I12: 80 | J12: 52 | K12: 48 | L12: 36 | M12: 68 | N12: F5 | O12: TC verificado (oficial). Hofstede: PDI–UAI verificado; LTO e IVR: matriz 2010 (referencia)
A13: CHN | B13: China | C13: Yuan renminbi | D13: CNY | E13: 6.7084 | F13: F7 | G13: 2026-09 | H13: 80 | I13: 20 | J13: 66 | K13: 30 | L13: 87 | M13: 24 | N13: F5 | O13: TC verificado (oficial). Hofstede: PDI–UAI verificado; LTO e IVR: matriz 2010 (referencia)
A14: JPN | B14: Japón | C14: Yen | D14: JPY | E14: 156.4171 | F14: F7 | G14: 2026-09 | H14: 54 | I14: 46 | J14: 95 | K14: 92 | L14: 88 | M14: 42 | N14: F5 | O14: TC verificado (oficial). Hofstede: Verificado (secundaria)

Sheet Productos
A1: Productos de exportación
A2: Costo FOB en USD por unidad de venta. Peso usado para calcular el flete.
A4: id | B4: Producto | C4: Código SA | D4: Unidad | E4: Peso (kg) | F4: Costo FOB (USD) | G4: Fuente | H4: Estado | I4: Nota | J4: Medio de referencia
A5: P01 | B5: Banano | C5: 0803.90 | D5: caja 18,14 kg | E5: 18.14 | F5: 8.36 | G5: F16 | H5: Verificado (oficial) | I5: Precio mínimo legal FOB por caja. | J5: Marítimo
A6: P02 | B6: Piña | C6: 0804.30 | D6: caja 12 kg | E6: 12 | F6: =ROUND(0.546*12,2) -> 6.55 | G6: F18 | H6: Referencia 2024 | I6: USD 546 por tonelada × 12 kg. | J6: Marítimo
A7: P03 | B7: Café oro (verde) | C7: 0901.11 | D7: saco 46 kg | E7: 46 | F7: =ROUND(46*2.20462*2.779,2) -> 281.83 | G7: F17 | H7: Derivado | I7: 46 kg × 2,20462 lb/kg × USD 2,779/lb. | J7: Marítimo
A8: P04 | B8: Café tostado | C8: 0901.21 | D8: caja 12 kg | E8: 12 | F8: =ROUND(12/0.82*2.20462*2.779*1.3,2) -> 116.56 | G8: F17 | H8: Derivado | I8: Café oro equivalente (merma de tueste 18 %) + 30 % por tueste y empaque. | J8: Marítimo
A9: P05 | B9: Melón | C9: 0807.19 | D9: caja 15 kg | E9: 15 | F9: =ROUND(43000000/58102000*15,2) -> 11.1 | G9: F19 | H9: Referencia 2024 | I9: USD 43 millones exportados ÷ 58 102 t (volumen 2024). | J9: Marítimo
A10: P06 | B10: Mango | C10: 0804.50 | D10: caja 4 kg | E10: 4 | F10: 5.5 | G10: F20 | H10: Referencia (años anteriores) | I10: Caja de 4 kg entre USD 4 y 6 en Ecuador; se usa el punto medio. | J10: Marítimo
A11: P07 | B11: Yuca | C11: 0714.10 | D11: caja 18 kg | E11: 18 | F11: =ROUND(146000000/135000000*18,2) -> 19.47 | G11: F19 | H11: Referencia 2024 | I11: USD 146 millones (2024) ÷ 135 000 t anuales (F21). | J11: Marítimo
A12: P08 | B12: Chayote | C12: 0709.99 | D12: caja 18 kg | E12: 18 | F12: 8 | G12: F22 | H12: Referencia (años anteriores) | I12: Precio internacional promedio de una caja. | J12: Marítimo
A13: P09 | B13: Plantas ornamentales | C13: 0602.90 | D13: caja 30 plantas | E13: 10 | F13: 25 | G13: F6 | H13: Estimado (referencia de mercado) | I13: USD 0,83 por planta en maceta pequeña. | J13: Aéreo
A14: P10 | B14: Aceite de palma | C14: 1511.10 | D14: tambor 190 kg | E14: 190 | F14: =ROUND(0.19*1007,2) -> 191.33 | G14: F23 | H14: Referencia 2025 | I14: USD 1 007 por tonelada (promedio 2025). | J14: Marítimo
A15: P11 | B15: Azúcar | C15: 1701.14 | D15: saco 50 kg | E15: 50 | F15: =ROUND(50*0.37,2) -> 18.5 | G15: F23 | H15: Referencia 2025 | I15: USD 0,37 por kg, precio mundial (promedio 2025). | J15: Marítimo
A16: P12 | B16: Jugo concentrado de piña | C16: 2009.49 | D16: tambor 250 kg | E16: 250 | F16: =ROUND(250*1.1,2) -> 275 | G16: F24 | H16: Referencia 2025 | I16: USD 1,10 por kg. | J16: Marítimo
A17: P13 | B17: Palmito preparado | C17: 2008.91 | D17: caja 24 frascos | E17: 12 | F17: 30 | G17: F6 | H17: Estimado (referencia de mercado) | I17: USD 1,25 por frasco. | J17: Marítimo
A18: P14 | B18: Cacao en grano | C18: 1801.00 | D18: saco 60 kg | E18: 60 | F18: =ROUND(60*7.8,2) -> 468 | G18: F23 | H18: Referencia 2025 | I18: USD 7,80 por kg (promedio 2025). | J18: Marítimo
A19: P15 | B19: Dispositivos médicos (catéteres) | C19: 9018.39 | D19: caja 100 unidades | E19: 8 | F19: 450 | G19: F6 | H19: Estimado (referencia de mercado) | I19: USD 4,50 por catéter desechable. | J19: Aéreo

Sheet Rutas
A1: Rutas desde Costa Rica
A2: Marítimo desde Moín, aéreo desde el Aeropuerto Juan Santamaría.
A4: Clave | B4: ISO | C4: País | D4: Medio | E4: Flete (USD/kg) | F4: % seguro | G4: Días | H4: Fuente | I4: Estado | J4: Nota
A5: =B5&"|"&D5 -> USA|Marítimo | B5: USA | C5: =INDEX(Paises!$B:$B,MATCH(B5,Paises!$A:$A,0)) -> Estados Unidos | D5: Marítimo | E5: 0.18 | F5: 0.005 | G5: 7 | H5: F6 | I5: Estimado (referencia de mercado) | J5: Tarifa general de referencia; seguro 0,3–0,5 % y tránsito según itinerarios habituales.
A6: =B6&"|"&D6 -> USA|Aéreo | B6: USA | C6: =INDEX(Paises!$B:$B,MATCH(B6,Paises!$A:$A,0)) -> Estados Unidos | D6: Aéreo | E6: 1.6 | F6: 0.0035 | G6: 1 | H6: F6 | I6: Estimado (referencia de mercado) | J6: Tarifa general de referencia; seguro 0,3–0,5 % y tránsito según itinerarios habituales.
A7: =B7&"|"&D7 -> NLD|Marítimo | B7: NLD | C7: =INDEX(Paises!$B:$B,MATCH(B7,Paises!$A:$A,0)) -> Países Bajos | D7: Marítimo | E7: =ROUND((3200+645)/20000,2) -> 0.19 | F7: 0.005 | G7: 18 | H7: F15 | I7: Derivado | J7: Flete reefer 40' USD 3 200 + manejo en Moín USD 645, sobre 20 t.
A8: =B8&"|"&D8 -> NLD|Aéreo | B8: NLD | C8: =INDEX(Paises!$B:$B,MATCH(B8,Paises!$A:$A,0)) -> Países Bajos | D8: Aéreo | E8: 2.8 | F8: 0.0035 | G8: 2 | H8: F6 | I8: Estimado (referencia de mercado) | J8: Tarifa general de referencia; seguro 0,3–0,5 % y tránsito según itinerarios habituales.
A9: =B9&"|"&D9 -> BEL|Marítimo | B9: BEL | C9: =INDEX(Paises!$B:$B,MATCH(B9,Paises!$A:$A,0)) -> Bélgica | D9: Marítimo | E9: =$E$7 -> 0.19 | F9: 0.005 | G9: 18 | H9: F6 | I9: Estimado (referencia de mercado) | J9: Igual a Moín–Rotterdam (misma ruta a Europa).
A10: =B10&"|"&D10 -> BEL|Aéreo | B10: BEL | C10: =INDEX(Paises!$B:$B,MATCH(B10,Paises!$A:$A,0)) -> Bélgica | D10: Aéreo | E10: 2.8 | F10: 0.0035 | G10: 2 | H10: F6 | I10: Estimado (referencia de mercado) | J10: Tarifa general de referencia; seguro 0,3–0,5 % y tránsito según itinerarios habituales.
A11: =B11&"|"&D11 -> DEU|Marítimo | B11: DEU | C11: =INDEX(Paises!$B:$B,MATCH(B11,Paises!$A:$A,0)) -> Alemania | D11: Marítimo | E11: =$E$7 -> 0.19 | F11: 0.005 | G11: 20 | H11: F6 | I11: Estimado (referencia de mercado) | J11: Igual a Moín–Rotterdam (misma ruta a Europa).
A12: =B12&"|"&D12 -> DEU|Aéreo | B12: DEU | C12: =INDEX(Paises!$B:$B,MATCH(B12,Paises!$A:$A,0)) -> Alemania | D12: Aéreo | E12: 2.9 | F12: 0.0035 | G12: 2 | H12: F6 | I12: Estimado (referencia de mercado) | J12: Tarifa general de referencia; seguro 0,3–0,5 % y tránsito según itinerarios habituales.
A13: =B13&"|"&D13 -> ESP|Marítimo | B13: ESP | C13: =INDEX(Paises!$B:$B,MATCH(B13,Paises!$A:$A,0)) -> España | D13: Marítimo | E13: =$E$7 -> 0.19 | F13: 0.005 | G13: 16 | H13: F6 | I13: Estimado (referencia de mercado) | J13: Igual a Moín–Rotterdam (misma ruta a Europa).
A14: =B14&"|"&D14 -> ESP|Aéreo | B14: ESP | C14: =INDEX(Paises!$B:$B,MATCH(B14,Paises!$A:$A,0)) -> España | D14: Aéreo | E14: 2.7 | F14: 0.0035 | G14: 2 | H14: F6 | I14: Estimado (referencia de mercado) | J14: Tarifa general de referencia; seguro 0,3–0,5 % y tránsito según itinerarios habituales.
A15: =B15&"|"&D15 -> GBR|Marítimo | B15: GBR | C15: =INDEX(Paises!$B:$B,MATCH(B15,Paises!$A:$A,0)) -> Reino Unido | D15: Marítimo | E15: =$E$7 -> 0.19 | F15: 0.005 | G15: 19 | H15: F6 | I15: Estimado (referencia de mercado) | J15: Igual a Moín–Rotterdam (misma ruta a Europa).
A16: =B16&"|"&D16 -> GBR|Aéreo | B16: GBR | C16: =INDEX(Paises!$B:$B,MATCH(B16,Paises!$A:$A,0)) -> Reino Unido | D16: Aéreo | E16: 2.9 | F16: 0.0035 | G16: 2 | H16: F6 | I16: Estimado (referencia de mercado) | J16: Tarifa general de referencia; seguro 0,3–0,5 % y tránsito según itinerarios habituales.
A17: =B17&"|"&D17 -> MEX|Marítimo | B17: MEX | C17: =INDEX(Paises!$B:$B,MATCH(B17,Paises!$A:$A,0)) -> México | D17: Marítimo | E17: 0.22 | F17: 0.005 | G17: 9 | H17: F6 | I17: Estimado (referencia de mercado) | J17: Tarifa general de referencia; seguro 0,3–0,5 % y tránsito según itinerarios habituales.
A18: =B18&"|"&D18 -> MEX|Aéreo | B18: MEX | C18: =INDEX(Paises!$B:$B,MATCH(B18,Paises!$A:$A,0)) -> México | D18: Aéreo | E18: 1.8 | F18: 0.0035 | G18: 1 | H18: F6 | I18: Estimado (referencia de mercado) | J18: Tarifa general de referencia; seguro 0,3–0,5 % y tránsito según itinerarios habituales.
A19: =B19&"|"&D19 -> CAN|Marítimo | B19: CAN | C19: =INDEX(Paises!$B:$B,MATCH(B19,Paises!$A:$A,0)) -> Canadá | D19: Marítimo | E19: 0.3 | F19: 0.005 | G19: 14 | H19: F6 | I19: Estimado (referencia de mercado) | J19: Tarifa general de referencia; seguro 0,3–0,5 % y tránsito según itinerarios habituales.
A20: =B20&"|"&D20 -> CAN|Aéreo | B20: CAN | C20: =INDEX(Paises!$B:$B,MATCH(B20,Paises!$A:$A,0)) -> Canadá | D20: Aéreo | E20: 2.2 | F20: 0.0035 | G20: 2 | H20: F6 | I20: Estimado (referencia de mercado) | J20: Tarifa general de referencia; seguro 0,3–0,5 % y tránsito según itinerarios habituales.
A21: =B21&"|"&D21 -> CHN|Marítimo | B21: CHN | C21: =INDEX(Paises!$B:$B,MATCH(B21,Paises!$A:$A,0)) -> China | D21: Marítimo | E21: 0.45 | F21: 0.005 | G21: 35 | H21: F6 | I21: Estimado (referencia de mercado) | J21: Tarifa general de referencia; seguro 0,3–0,5 % y tránsito según itinerarios habituales.
A22: =B22&"|"&D22 -> CHN|Aéreo | B22: CHN | C22: =INDEX(Paises!$B:$B,MATCH(B22,Paises!$A:$A,0)) -> China | D22: Aéreo | E22: 3.8 | F22: 0.0035 | G22: 3 | H22: F6 | I22: Estimado (referencia de mercado) | J22: Tarifa general de referencia; seguro 0,3–0,5 % y tránsito según itinerarios habituales.
A23: =B23&"|"&D23 -> JPN|Marítimo | B23: JPN | C23: =INDEX(Paises!$B:$B,MATCH(B23,Paises!$A:$A,0)) -> Japón | D23: Marítimo | E23: 0.48 | F23: 0.005 | G23: 32 | H23: F6 | I23: Estimado (referencia de mercado) | J23: Tarifa general de referencia; seguro 0,3–0,5 % y tránsito según itinerarios habituales.
A24: =B24&"|"&D24 -> JPN|Aéreo | B24: JPN | C24: =INDEX(Paises!$B:$B,MATCH(B24,Paises!$A:$A,0)) -> Japón | D24: Aéreo | E24: 3.9 | F24: 0.0035 | G24: 3 | H24: F6 | I24: Estimado (referencia de mercado) | J24: Tarifa general de referencia; seguro 0,3–0,5 % y tránsito según itinerarios habituales.

Sheet Aranceles
A1: Aranceles NMF ad valorem
A2: Uno por cada combinación de los casos. Agregar filas para ampliar la matriz.
A4: Clave | B4: ISO | C4: id producto | D4: País | E4: Producto | F4: % ad valorem | G4: Fuente | H4: Fecha | I4: Estado | J4: Nota
A5: =B5&"|"&C5 -> USA|P01 | B5: USA | C5: P01 | D5: =INDEX(Paises!$B:$B,MATCH(B5,Paises!$A:$A,0)) -> Estados Unidos | E5: =INDEX(Productos!$B:$B,MATCH(C5,Productos!$A:$A,0)) -> Banano | F5: 0 | G5: F10 | H5: 2026-10-09 | I5: Verificado (secundaria) | J5: HTS 0803.90.00: Free.
A6: =B6&"|"&C6 -> NLD|P02 | B6: NLD | C6: P02 | D6: =INDEX(Paises!$B:$B,MATCH(B6,Paises!$A:$A,0)) -> Países Bajos | E6: =INDEX(Productos!$B:$B,MATCH(C6,Productos!$A:$A,0)) -> Piña | F6: 0.058 | G6: F11 | H6: 2026-10-09 | I6: Verificado (secundaria) | J6: CN 0804 30 00: 5,8 %.
A7: =B7&"|"&C7 -> DEU|P03 | B7: DEU | C7: P03 | D7: =INDEX(Paises!$B:$B,MATCH(B7,Paises!$A:$A,0)) -> Alemania | E7: =INDEX(Productos!$B:$B,MATCH(C7,Productos!$A:$A,0)) -> Café oro (verde) | F7: 0 | G7: F11 | H7: 2026-10-09 | I7: Referencia (histórico UE) | J7: CN 0901 11 00: 0 %, tasa histórica de la UE para café verde.
A8: =B8&"|"&C8 -> JPN|P04 | B8: JPN | C8: P04 | D8: =INDEX(Paises!$B:$B,MATCH(B8,Paises!$A:$A,0)) -> Japón | E8: =INDEX(Productos!$B:$B,MATCH(C8,Productos!$A:$A,0)) -> Café tostado | F8: 0.12 | G8: F8 | H8: 2026-10-09 | I8: Verificado (oficial) | J8: 0901.21.000: tasa OMC 12 %.
A9: =B9&"|"&C9 -> GBR|P05 | B9: GBR | C9: P05 | D9: =INDEX(Paises!$B:$B,MATCH(B9,Paises!$A:$A,0)) -> Reino Unido | E9: =INDEX(Productos!$B:$B,MATCH(C9,Productos!$A:$A,0)) -> Melón | F9: 0.08 | G9: F12 | H9: 2026-10-09 | I9: Verificado (secundaria) | J9: 0807 19 00 50: 8 %.
A10: =B10&"|"&C10 -> CAN|P06 | B10: CAN | C10: P06 | D10: =INDEX(Paises!$B:$B,MATCH(B10,Paises!$A:$A,0)) -> Canadá | E10: =INDEX(Productos!$B:$B,MATCH(C10,Productos!$A:$A,0)) -> Mango | F10: 0 | G10: F9 | H10: 2026-10-09 | I10: Verificado (oficial) | J10: 0804.50.00: Free.
A11: =B11&"|"&C11 -> USA|P07 | B11: USA | C11: P07 | D11: =INDEX(Paises!$B:$B,MATCH(B11,Paises!$A:$A,0)) -> Estados Unidos | E11: =INDEX(Productos!$B:$B,MATCH(C11,Productos!$A:$A,0)) -> Yuca | F11: 0.113 | G11: F10 | H11: 2026-10-09 | I11: Verificado (secundaria) | J11: HTS 0714.10.20.00: 11,3 %.
A12: =B12&"|"&C12 -> ESP|P09 | B12: ESP | C12: P09 | D12: =INDEX(Paises!$B:$B,MATCH(B12,Paises!$A:$A,0)) -> España | E12: =INDEX(Productos!$B:$B,MATCH(C12,Productos!$A:$A,0)) -> Plantas ornamentales | F12: 0.065 | G12: F11 | H12: 2026-10-09 | I12: Verificado (secundaria) | J12: CN 0602 90 70 plantas de interior: 6,5 %.
A13: =B13&"|"&C13 -> MEX|P15 | B13: MEX | C13: P15 | D13: =INDEX(Paises!$B:$B,MATCH(B13,Paises!$A:$A,0)) -> México | E13: =INDEX(Productos!$B:$B,MATCH(C13,Productos!$A:$A,0)) -> Dispositivos médicos (catéteres) | F13: 0 | G13: F13 | H13: 2026-10-09 | I13: Verificado (secundaria) | J13: TIGIE 9018.39.01: exento.
A14: =B14&"|"&C14 -> CHN|P12 | B14: CHN | C14: P12 | D14: =INDEX(Paises!$B:$B,MATCH(B14,Paises!$A:$A,0)) -> China | E14: =INDEX(Productos!$B:$B,MATCH(C14,Productos!$A:$A,0)) -> Jugo concentrado de piña | F14: 0.05 | G14: F14 | H14: 2026-10-09 | I14: Verificado (secundaria) | J14: 2009.49.00: NMF 5 %.

Sheet Demanda
A1: Demanda de mercado
A2: Parámetros del juego. Precio de referencia = costo puesto en destino por el medio de referencia × (1 + margen).
A4: Clave | B4: ISO | C4: id producto | D4: País | E4: Producto | F4: Precio de referencia (USD) | G4: Demanda base (unid./ronda) | H4: Fuente | I4: Estado | J4: Medio de referencia
A5: =B5&"|"&C5 -> USA|P01 | B5: USA | C5: P01 | D5: =INDEX(Paises!$B:$B,MATCH(B5,Paises!$A:$A,0)) -> Estados Unidos | E5: =INDEX(Productos!$B:$B,MATCH(C5,Productos!$A:$A,0)) -> Banano | F5: =ROUND((INDEX(Productos!$F:$F,MATCH(C5,Productos!$A:$A,0))+INDEX(Productos!$E:$E,MATCH(C5,Productos!$A:$A,0))*INDEX(Rutas!$E:$E,MATCH(B5&"|"&J5,Rutas!$A:$A,0)))*(1+INDEX(Rutas!$F:$F,MATCH(B5&"|"&J5,Rutas!$A:$A,0)))*(1+INDEX(Aranceles!$F:$F,MATCH(B5&"|"&C5,Aranceles!$A:$A,0)))*(1+Parametros!$B$10),2) -> 14.6 | G5: 4000 | H5: F6 | I5: Parámetro del juego | J5: =INDEX(Productos!$J:$J,MATCH(C5,Productos!$A:$A,0)) -> Marítimo
A6: =B6&"|"&C6 -> NLD|P02 | B6: NLD | C6: P02 | D6: =INDEX(Paises!$B:$B,MATCH(B6,Paises!$A:$A,0)) -> Países Bajos | E6: =INDEX(Productos!$B:$B,MATCH(C6,Productos!$A:$A,0)) -> Piña | F6: =ROUND((INDEX(Productos!$F:$F,MATCH(C6,Productos!$A:$A,0))+INDEX(Productos!$E:$E,MATCH(C6,Productos!$A:$A,0))*INDEX(Rutas!$E:$E,MATCH(B6&"|"&J6,Rutas!$A:$A,0)))*(1+INDEX(Rutas!$F:$F,MATCH(B6&"|"&J6,Rutas!$A:$A,0)))*(1+INDEX(Aranceles!$F:$F,MATCH(B6&"|"&C6,Aranceles!$A:$A,0)))*(1+Parametros!$B$10),2) -> 11.74 | G6: 4500 | H6: F6 | I6: Parámetro del juego | J6: =INDEX(Productos!$J:$J,MATCH(C6,Productos!$A:$A,0)) -> Marítimo
A7: =B7&"|"&C7 -> DEU|P03 | B7: DEU | C7: P03 | D7: =INDEX(Paises!$B:$B,MATCH(B7,Paises!$A:$A,0)) -> Alemania | E7: =INDEX(Productos!$B:$B,MATCH(C7,Productos!$A:$A,0)) -> Café oro (verde) | F7: =ROUND((INDEX(Productos!$F:$F,MATCH(C7,Productos!$A:$A,0))+INDEX(Productos!$E:$E,MATCH(C7,Productos!$A:$A,0))*INDEX(Rutas!$E:$E,MATCH(B7&"|"&J7,Rutas!$A:$A,0)))*(1+INDEX(Rutas!$F:$F,MATCH(B7&"|"&J7,Rutas!$A:$A,0)))*(1+INDEX(Aranceles!$F:$F,MATCH(B7&"|"&C7,Aranceles!$A:$A,0)))*(1+Parametros!$B$10),2) -> 365.03 | G7: 90 | H7: F6 | I7: Parámetro del juego | J7: =INDEX(Productos!$J:$J,MATCH(C7,Productos!$A:$A,0)) -> Marítimo
A8: =B8&"|"&C8 -> JPN|P04 | B8: JPN | C8: P04 | D8: =INDEX(Paises!$B:$B,MATCH(B8,Paises!$A:$A,0)) -> Japón | E8: =INDEX(Productos!$B:$B,MATCH(C8,Productos!$A:$A,0)) -> Café tostado | F8: =ROUND((INDEX(Productos!$F:$F,MATCH(C8,Productos!$A:$A,0))+INDEX(Productos!$E:$E,MATCH(C8,Productos!$A:$A,0))*INDEX(Rutas!$E:$E,MATCH(B8&"|"&J8,Rutas!$A:$A,0)))*(1+INDEX(Rutas!$F:$F,MATCH(B8&"|"&J8,Rutas!$A:$A,0)))*(1+INDEX(Aranceles!$F:$F,MATCH(B8&"|"&C8,Aranceles!$A:$A,0)))*(1+Parametros!$B$10),2) -> 172.1 | G8: 150 | H8: F6 | I8: Parámetro del juego | J8: =INDEX(Productos!$J:$J,MATCH(C8,Productos!$A:$A,0)) -> Marítimo
A9: =B9&"|"&C9 -> GBR|P05 | B9: GBR | C9: P05 | D9: =INDEX(Paises!$B:$B,MATCH(B9,Paises!$A:$A,0)) -> Reino Unido | E9: =INDEX(Productos!$B:$B,MATCH(C9,Productos!$A:$A,0)) -> Melón | F9: =ROUND((INDEX(Productos!$F:$F,MATCH(C9,Productos!$A:$A,0))+INDEX(Productos!$E:$E,MATCH(C9,Productos!$A:$A,0))*INDEX(Rutas!$E:$E,MATCH(B9&"|"&J9,Rutas!$A:$A,0)))*(1+INDEX(Rutas!$F:$F,MATCH(B9&"|"&J9,Rutas!$A:$A,0)))*(1+INDEX(Aranceles!$F:$F,MATCH(B9&"|"&C9,Aranceles!$A:$A,0)))*(1+Parametros!$B$10),2) -> 18.93 | G9: 3600 | H9: F6 | I9: Parámetro del juego | J9: =INDEX(Productos!$J:$J,MATCH(C9,Productos!$A:$A,0)) -> Marítimo
A10: =B10&"|"&C10 -> CAN|P06 | B10: CAN | C10: P06 | D10: =INDEX(Paises!$B:$B,MATCH(B10,Paises!$A:$A,0)) -> Canadá | E10: =INDEX(Productos!$B:$B,MATCH(C10,Productos!$A:$A,0)) -> Mango | F10: =ROUND((INDEX(Productos!$F:$F,MATCH(C10,Productos!$A:$A,0))+INDEX(Productos!$E:$E,MATCH(C10,Productos!$A:$A,0))*INDEX(Rutas!$E:$E,MATCH(B10&"|"&J10,Rutas!$A:$A,0)))*(1+INDEX(Rutas!$F:$F,MATCH(B10&"|"&J10,Rutas!$A:$A,0)))*(1+INDEX(Aranceles!$F:$F,MATCH(B10&"|"&C10,Aranceles!$A:$A,0)))*(1+Parametros!$B$10),2) -> 8.42 | G10: 1000 | H10: F6 | I10: Parámetro del juego | J10: =INDEX(Productos!$J:$J,MATCH(C10,Productos!$A:$A,0)) -> Marítimo
A11: =B11&"|"&C11 -> USA|P07 | B11: USA | C11: P07 | D11: =INDEX(Paises!$B:$B,MATCH(B11,Paises!$A:$A,0)) -> Estados Unidos | E11: =INDEX(Productos!$B:$B,MATCH(C11,Productos!$A:$A,0)) -> Yuca | F11: =ROUND((INDEX(Productos!$F:$F,MATCH(C11,Productos!$A:$A,0))+INDEX(Productos!$E:$E,MATCH(C11,Productos!$A:$A,0))*INDEX(Rutas!$E:$E,MATCH(B11&"|"&J11,Rutas!$A:$A,0)))*(1+INDEX(Rutas!$F:$F,MATCH(B11&"|"&J11,Rutas!$A:$A,0)))*(1+INDEX(Aranceles!$F:$F,MATCH(B11&"|"&C11,Aranceles!$A:$A,0)))*(1+Parametros!$B$10),2) -> 31.75 | G11: 1200 | H11: F6 | I11: Parámetro del juego | J11: =INDEX(Productos!$J:$J,MATCH(C11,Productos!$A:$A,0)) -> Marítimo
A12: =B12&"|"&C12 -> ESP|P09 | B12: ESP | C12: P09 | D12: =INDEX(Paises!$B:$B,MATCH(B12,Paises!$A:$A,0)) -> España | E12: =INDEX(Productos!$B:$B,MATCH(C12,Productos!$A:$A,0)) -> Plantas ornamentales | F12: =ROUND((INDEX(Productos!$F:$F,MATCH(C12,Productos!$A:$A,0))+INDEX(Productos!$E:$E,MATCH(C12,Productos!$A:$A,0))*INDEX(Rutas!$E:$E,MATCH(B12&"|"&J12,Rutas!$A:$A,0)))*(1+INDEX(Rutas!$F:$F,MATCH(B12&"|"&J12,Rutas!$A:$A,0)))*(1+INDEX(Aranceles!$F:$F,MATCH(B12&"|"&C12,Aranceles!$A:$A,0)))*(1+Parametros!$B$10),2) -> 69.47 | G12: 400 | H12: F6 | I12: Parámetro del juego | J12: =INDEX(Productos!$J:$J,MATCH(C12,Productos!$A:$A,0)) -> Aéreo
A13: =B13&"|"&C13 -> MEX|P15 | B13: MEX | C13: P15 | D13: =INDEX(Paises!$B:$B,MATCH(B13,Paises!$A:$A,0)) -> México | E13: =INDEX(Productos!$B:$B,MATCH(C13,Productos!$A:$A,0)) -> Dispositivos médicos (catéteres) | F13: =ROUND((INDEX(Productos!$F:$F,MATCH(C13,Productos!$A:$A,0))+INDEX(Productos!$E:$E,MATCH(C13,Productos!$A:$A,0))*INDEX(Rutas!$E:$E,MATCH(B13&"|"&J13,Rutas!$A:$A,0)))*(1+INDEX(Rutas!$F:$F,MATCH(B13&"|"&J13,Rutas!$A:$A,0)))*(1+INDEX(Aranceles!$F:$F,MATCH(B13&"|"&C13,Aranceles!$A:$A,0)))*(1+Parametros!$B$10),2) -> 582.53 | G13: 100 | H13: F6 | I13: Parámetro del juego | J13: =INDEX(Productos!$J:$J,MATCH(C13,Productos!$A:$A,0)) -> Aéreo
A14: =B14&"|"&C14 -> CHN|P12 | B14: CHN | C14: P12 | D14: =INDEX(Paises!$B:$B,MATCH(B14,Paises!$A:$A,0)) -> China | E14: =INDEX(Productos!$B:$B,MATCH(C14,Productos!$A:$A,0)) -> Jugo concentrado de piña | F14: =ROUND((INDEX(Productos!$F:$F,MATCH(C14,Productos!$A:$A,0))+INDEX(Productos!$E:$E,MATCH(C14,Productos!$A:$A,0))*INDEX(Rutas!$E:$E,MATCH(B14&"|"&J14,Rutas!$A:$A,0)))*(1+INDEX(Rutas!$F:$F,MATCH(B14&"|"&J14,Rutas!$A:$A,0)))*(1+INDEX(Aranceles!$F:$F,MATCH(B14&"|"&C14,Aranceles!$A:$A,0)))*(1+Parametros!$B$10),2) -> 511.14 | G14: 60 | H14: F6 | I14: Parámetro del juego | J14: =INDEX(Productos!$J:$J,MATCH(C14,Productos!$A:$A,0)) -> Marítimo

Sheet Parametros
A1: Parámetros de la partida
A2: Valores que la docente define al crear la partida (RF-03).
A4: Parámetro | B4: Valor | C4: Nota
A5: Capital inicial por equipo (USD) | B5: 50000 | C5: Igual para todos los equipos.
A6: Elasticidad precio de la demanda | B6: 1.5 | C6: A mayor valor, más castiga un precio alto.
A7: Número de rondas | B7: 4
A8: Duración de ronda (min) | B8: 8 | C8: Temporizador del panel docente (RF-05).
A9: País de origen | B9: Costa Rica
A10: Margen de mercado sobre costo puesto en destino | B10: 0.25 | C10: Calibra el precio de referencia de la hoja Demanda.

Sheet Fuentes
A1: Fuentes
A2: Para citar en APA 7, use el nombre y la URL de cada fuente.
A4: id | B4: Fuente | C4: URL
A5: F1 | B5: UN Comtrade | C5: https://comtradeplus.un.org
A6: F2 | B6: WITS, Banco Mundial | C6: https://wits.worldbank.org
A7: F4 | B7: BCCR, indicadores económicos | C7: https://www.bccr.fi.cr/indicadores-economicos
A8: F5 | B8: Hofstede, Hofstede y Minkov (2010), tablas publicadas (UNC, PMC, Rework) | C8: https://geerthofstede.com/research-and-vsm/dimension-data-matrix/
A9: F6 | B9: Estimación del equipo con referencias de mercado
A10: F7 | B10: Federal Reserve, G.5 Foreign Exchange Rates (FRED), sep. 2026 | C10: https://fred.stlouisfed.org/release/tables?eid=26693&rid=15
A11: F8 | B11: Aduanas de Japón, arancel al 1/4/2026 | C11: https://www.customs.go.jp/english/tariff/2026_04_01/data/e_09.htm
A12: F9 | B12: CBSA, Customs Tariff, cap. 08 | C12: https://cbsa-asfc.gc.ca/trade-commerce/tariff-tarif/2024/01-99/ch08-2024-eng.pdf
A13: F10 | B13: USITC Harmonized Tariff Schedule (vía agregadores) | C13: https://hts.usitc.gov
A14: F11 | B14: TARIC de la UE (vía thetradehub.eu / hsciq.com) | C14: https://ec.europa.eu/taxation_customs/dds2/taric/
A15: F12 | B15: UK Trade Tariff (vía treayo.com) | C15: https://www.trade-tariff.service.gov.uk
A16: F13 | B16: TIGIE México (vía camtomx.com) | C16: https://www.snice.gob.mx
A17: F14 | B17: Arancel de China 2026 (vía htshub.com) | C17: https://www.htshub.com/cn-hs/detail/2009490000
A18: F15 | B18: Maersk, tarifas Costa Rica 2025-2026 | C18: https://www.maersk.com/news/articles/2026/09/16/terminal-handling-service-revision-costa-rica
A19: F16 | B19: Decreto de precio mínimo de la caja de banano (2020) | C19: https://delfino.cr/2019/12/gobierno-sube-precio-minimo-de-banano-de-exportacion-en-87
A20: F17 | B20: ICE Futures US, café arábica, 28/09/2026 | C20: https://es.dailyforex.com/forex-technical-analysis/2026/09/cafe-arabica-en-mexico-pone-a-prueba-soporte-clave-28-septiembre-2026/250132
A21: F18 | B21: IndexBox, precio medio de exportación de piña de Costa Rica 2024 | C21: https://www.indexbox.io/store/costa-rica-pineapples-market-report-analysis-and-forecast-to-2020/
... A27: F24 | B27: Tridge, precio unitario de jugo de piña de Costa Rica (2025) | C27: https://www.tridge.com/intelligences/pineapple-juice

Sheet Backlog
A1: Product Backlog
A2: Responsable y estado se actualizan en cada revisión del sprint.
A4: RF | B4: Requerimiento | C4: Prioridad | D4: Sprint | E4: Entregable | F4: Rama | G4: Responsable | H4: Estado
A5: RF-01 | B5: Registrar e iniciar sesión como docente. | C5: Alta | D5: 2 | E5: Registro e inicio de sesión del docente. | F5: feature/rf-01-login-docente | H5: Pendiente
A6: RF-02 | B6: Ingresar como estudiante con código y alias, sin crear cuenta. | C6: Alta | D6: 1 | E6: Ingreso con código y alias, y sala de espera. | F6: feature/rf-02-ingreso-estudiante | H6: Pendiente
A7: RF-03 | B7: Crear una partida: rondas, duración, capital, países y productos. | C7: Alta | D7: 1 | E7: Asistente de partida y código de acceso. | F7: feature/rf-03-crear-partida | H7: Pendiente
A8: RF-04 | B8: Conformar equipos de forma automática o manual. | C8: Alta | D8: 2 | E8: Conformación de equipos. | F8: feature/rf-04-equipos | H8: Pendiente
A9: RF-05 | B9: Iniciar, pausar y cerrar rondas con temporizador visible. | C9: Alta | D9: 1 | E9: Panel del docente. | F9: feature/rf-05-panel-ronda | H9: Pendiente
A10: RF-06 | B10: Consultar la ficha de cada país con fuente y fecha. | C10: Alta | D10: 1 | E10: Muestra de 10 países y ficha de país. | F10: feature/rf-06-ficha-pais | H10: Pendiente
A11: RF-07 | B11: Consultar la ficha de cada producto. | C11: Media | D11: 2 | E11: Ficha de producto. | F11: feature/rf-07-ficha-producto | H11: Pendiente
A12: RF-08 | B12: Registrar la decisión del equipo. | C12: Alta | D12: 1 | E12: Formulario de decisión. | F12: feature/rf-08-decision | H12: Pendiente
A13: RF-09 | B13: Calcular FOB, flete, seguro, CIF y arancel, y convertir con el tipo de cambio. | C13: Alta | D13: 1 | E13: Fórmulas de costos verificadas con 10 casos. | F13: feature/rf-09-costos | H13: Pendiente
A14: RF-10 | B14: Calcular ventas, utilidad y capital según precio y competencia. | C14: Alta | D14: 1 | E14: Regla de ventas y pruebas de precio. | F14: feature/rf-10-ventas-utilidad | H14: Pendiente
A15: RF-11 | B15: Mostrar el resultado de la ronda con desglose y explicación. | C15: Alta | D15: 1 | E15: Pantalla de resultados. | F15: feature/rf-11-resultados | H15: Pendiente
A16: RF-12 | B16: Mostrar el ranking de equipos. | C16: Alta | D16: 2 | E16: Ranking. | F16: feature/rf-12-ranking | H16: Pendiente
... A20: RF-16 | B20: Ofrecer un modo de demostración sin registro. | C20: Baja | D20: 2 | E20: Modo demostración. | F20: feature/rf-16-modo-demo | H20: Pendiente
B23: Requerimientos | C23: =COUNTA(A5:A20) -> 16
B24: En Sprint 1 | C24: =COUNTIF(D5:D20,1) -> 8
B25: % en Sprint 1 | C25: =C24/C23 -> 0.5
B26: Sprint 1 terminados | C26: =COUNTIFS(D5:D20,1,H5:H20,"Terminado") -> 0
B27: Avance del Sprint 1 | C27: =IF(C24=0,0,C26/C24) -> 0
B28: Avance del producto | C28: =COUNTIF(H5:H20,"Terminado")/C23 -> 0
